tagup/__init__.py
tagup/evaluation.py
tagup/exceptions.py
tagup/grammar.lark
tagup/language.py
tagup/stack.py
tagup/traversal.py
tagup-0.2.3.dist-info/LICENSE
tagup-0.2.3.dist-info/WHEEL
tagup-0.2.3.dist-info/METADATA
tagup-0.2.3.dist-info/RECORD
