Metadata-Version: 2.1
Name: tagup
Version: 0.2.3
Summary: Reference implementation of the Tagup Language
Home-page: https://fairburn.dev/tagup/
License: MIT
Keywords: markup,language,templating
Author: Garrett Fairburn
Author-email: garrett@fairburn.dev
Requires-Python: >=3.8,<4.0
Classifier: License :: OSI Approved :: MIT License
Classifier: Programming Language :: Python :: 3
Classifier: Programming Language :: Python :: 3.8
Requires-Dist: lark-parser (>=0.8.5,<0.9.0)
